vimeworld/__init__.py
vimeworld/client.py
vimeworld/guilds.py
vimeworld/users.py
vimeworld-0.0.1.dist-info/LICENSE
vimeworld-0.0.1.dist-info/METADATA
vimeworld-0.0.1.dist-info/WHEEL
vimeworld-0.0.1.dist-info/top_level.txt
vimeworld-0.0.1.dist-info/RECORD
