Metadata-Version: 2.1
Name: vimeworld
Version: 0.0.1
Summary: SDK для работы с API VimeWorld
Home-page: https://github.com/xtraswed/vimeworld
Author: xtraswed
Author-email: xtraswed@gmail.com
Project-URL: GitHub, https://github.com/xtraswed
Keywords: vimeworld VimeWorld Vimeworld vimeWorld xtraswed Xtraswed minecraft api sdk SDK
Classifier: Programming Language :: Python :: 3.11
Classifier: License :: OSI Approved :: MIT License
Classifier: Operating System :: OS Independent
Requires-Python: >=3.8
License-File: LICENSE
Requires-Dist: requests (>=2.25.1)
